pycounts_rbattu/__init__.py
pycounts_rbattu/plotting.py
pycounts_rbattu/pycounts_rbattu.py
pycounts_rbattu-0.1.0.dist-info/LICENSE
pycounts_rbattu-0.1.0.dist-info/METADATA
pycounts_rbattu-0.1.0.dist-info/WHEEL
pycounts_rbattu-0.1.0.dist-info/RECORD
