Metadata-Version: 2.1
Name: pycounts_rbattu
Version: 0.1.0
Summary: Calculate word counts in a text file!
License: MIT
Author: Riddhi Battu
Requires-Python: >=3.9
Classifier: License :: OSI Approved :: MIT License
Classifier: Programming Language :: Python :: 3
Classifier: Programming Language :: Python :: 3.9
Classifier: Programming Language :: Python :: 3.10
Classifier: Programming Language :: Python :: 3.11
Classifier: Programming Language :: Python :: 3.12
Requires-Dist: matplotlib (>=3.8.4)
Requires-Dist: numpy (==1.21.5) ; python_version >= "3.7" and python_version < "3.11"
